[
  {
    "headline": "Prime Minister greets people of Goa on Goa Statehood Day",
    "fullText": "<p>Prime Minister greets people of Goa on Goa Statehood Day</p><p>The Prime Minister, Shri Narendra Modi, today extended his greetings to the people of Goa on the occasion of Goa Statehood Day. The Prime Minister said that Goa is widely known for its vibrant culture, rich heritage, natural beauty and warm-hearted people. The Prime Minister noted that the occasion is an opportunity to remember with gratitude all those who worked tirelessly for the progress and identity of Goa. The Prime Minister expressed hope that Goa will continue to prosper and play an important role in building a Viksit Bharat. Shri Modi also prayed for the good health and prosperity of every Goan. The Prime Minister wrote on X; “Greetings to the people of Goa on the special occasion of Goa Statehood Day. Goa’s vibrant culture, rich heritage, natural beauty and warm-hearted people are widely known. This day is also an opportunity to remember with gratitude all those who worked tirelessly for its progress and identity. May Goa continue to prosper and play an important role in building a Viksit Bharat. Praying for the good health and prosperity of every Goan.”</p><p>Greetings to the people of Goa on the special occasion of Goa Statehood Day. Goa’s vibrant culture, rich heritage, natural beauty and warm-hearted people are widely known. This day is also an opportunity to remember with gratitude all those who worked tirelessly for its progress…</p>",
    "summaryText": "Prime Minister greets people of Goa on Goa Statehood DayThe Prime Minister, Shri Narendra Modi, today extended his greetings to the people of Goa on the occasion of Goa Statehood Day. The Prime Minister said that Goa is widely known for its vibrant culture, rich heritage, natural beauty and warm-hearted people. The Prime Minister noted that the occasion is an opportunity to remember with gratitude...",
    "category": "Prime Minister's Office",
    "imageUrl": "https://static.pib.gov.in/WriteReadData/specificdocs/photo/2021/aug/ph202183101.png",
    "imageUrls": [
      "https://static.pib.gov.in/WriteReadData/specificdocs/photo/2021/aug/ph202183101.png"
    ],
    "articleUrl": "https://www.pib.gov.in/PressReleaseIframePage.aspx?PRID=2266896&reg=3&lang=1"
  }
]